SCBert/SCBert.py
SCBert/__init__.py
SCBert/fast-multi-rake.py
SCBert/load_data.py
SCBert/data/CLS-fr.csv
SCBert-0.2.dist-info/LICENSE
SCBert-0.2.dist-info/METADATA
SCBert-0.2.dist-info/WHEEL
SCBert-0.2.dist-info/top_level.txt
SCBert-0.2.dist-info/RECORD
