Metadata-Version: 2.1
Name: SCBert
Version: 0.2
Summary: A small package to do Sentence Clustering with BERT (SCBert)
Home-page: https://github.com/KevinFerin/SCBert
Author: Kevin Ferin
Author-email: siktime92@gmail.com
License: UNKNOWN
Keywords: sentence clustering,bert,keyword extraction,sentence embedding,neural networks,flaubert,camembert
Platform: UNKNOWN
Classifier: Programming Language :: Python :: 3
Classifier: License :: OSI Approved :: MIT License
Classifier: Operating System :: OS Independent
Requires-Dist: tqdm (==4.42.1)
Requires-Dist: stop-words (==2018.7.23)
Requires-Dist: transformers (==2.5.1)
Requires-Dist: multi-rake (==0.0.1)
Requires-Dist: numpy (==1.18.1)
Requires-Dist: matplotlib (==3.1.1)
Requires-Dist: torch (==1.3.1)
Requires-Dist: scikit-learn (==0.22.2.post1)
